{"dependencies":[{"name":"fbjs/lib/UserAgent","loc":{"line":16,"column":24}},{"name":"fbjs/lib/invariant","loc":{"line":18,"column":24}}],"generated":{"js":"\"use strict\";function r(r){for(var e=r.cloneRange(),n=[],a=r.endContainer;null!=a;a=a.parentNode){var o=a===r.commonAncestorContainer;o?e.setStart(r.startContainer,r.startOffset):e.setStart(e.endContainer,0);var s=Array.from(e.getClientRects());if(n.push(s),o){var i;return n.reverse(),(i=[]).concat.apply(i,n)}e.setEndBefore(a)}t(!1)}var e=require(\"fbjs/lib/UserAgent\"),t=require(\"fbjs/lib/invariant\"),n=e.isBrowser(\"Chrome\"),a=n?r:function(r){return Array.from(r.getClientRects())};module.exports=a;"},"hash":"03525fac40533fe086e653d3f2c4628d"}