{"dependencies":[{"name":"../rule/","loc":{"line":1,"column":18}},{"name":"../util","loc":{"line":2,"column":29}}],"generated":{"js":"\"use strict\";function e(e){return e&&e.__esModule?e:{default:e}}function r(e,r,u,d,l){var a=[];if(e.required||!e.required&&d.hasOwnProperty(e.field)){if((0,i.isEmptyValue)(r)&&!e.required)return u();t.default.required(e,r,d,a,l),(0,i.isEmptyValue)(r)||t.default.type(e,r,d,a,l)}u(a)}Object.defineProperty(exports,\"__esModule\",{value:!0});var u=require(\"../rule/\"),t=e(u),i=require(\"../util\");exports.default=r;"},"hash":"03cc4be0fa1ed1d64635e47c18cd8a3c"}